Metadata-Version: 2.1
Name: screenshotscloud
Version: 1.0.4
Summary: ScreenshotsCloud Python screenshot generator
Home-page: https://screenshots.cloud/
Author: Chris Hutchinson
Author-email: chris@equalkit.com
License: MIT
Keywords: screenshots,screenshots.cloud,firefox,browser
Platform: UNKNOWN
Classifier: Development Status :: 5 - Production/Stable
Classifier: Intended Audience :: Developers
Classifier: Natural Language :: English
Classifier: License :: OSI Approved :: MIT License
Classifier: Programming Language :: Python
Classifier: Programming Language :: Python :: 2.6
Classifier: Programming Language :: Python :: 2.7
Classifier: Programming Language :: Python :: 3
Classifier: Programming Language :: Python :: 3.3
Classifier: Programming Language :: Python :: 3.4
Classifier: Programming Language :: Python :: 3.5
Classifier: Programming Language :: Python :: 3.6
Classifier: Programming Language :: Python :: Implementation :: CPython
Classifier: Programming Language :: Python :: Implementation :: PyPy
